{"perfEntries":[{"name":"http://localhost:5173/03-context-provider","entryType":"navigation","startTime":0,"duration":204.5,"initiatorType":"navigation","nextHopProtocol":"http/1.1","workerStart":0,"redirectStart":0,"redirectEnd":0,"fetchStart":0.19999998807907104,"domainLookupStart":2.199999988079071,"domainLookupEnd":2.199999988079071,"connectStart":2.199999988079071,"connectEnd":2.800000011920929,"secureConnectionStart":0,"requestStart":2.9000000059604645,"responseStart":17.69999998807907,"responseEnd":19.099999994039536,"transferSize":1187,"encodedBodySize":887,"decodedBodySize":887,"serverTiming":[],"unloadEventStart":0,"unloadEventEnd":0,"domInteractive":40,"domContentLoadedEventStart":202.5,"domContentLoadedEventEnd":202.5,"domComplete":204.5,"loadEventStart":204.5,"loadEventEnd":204.5,"type":"navigate","redirectCount":0},{"name":"http://localhost:5173/@vite/client","entryType":"resource","startTime":28.400000005960464,"duration":10.400000005960464,"initiatorType":"script","nextHopProtocol":"http/1.1","workerStart":0,"redirectStart":0,"redirectEnd":0,"fetchStart":28.400000005960464,"domainLookupStart":28.400000005960464,"domainLookupEnd":28.400000005960464,"connectStart":28.400000005960464,"connectEnd":28.400000005960464,"secureConnectionStart":0,"requestStart":31.19999998807907,"responseStart":36.900000005960464,"responseEnd":38.80000001192093,"transferSize":76759,"encodedBodySize":76459,"decodedBodySize":76459,"serverTiming":[]},{"name":"http://localhost:5173/src/main.jsx?t=1665146093538","entryType":"resource","startTime":28.900000005960464,"duration":11.699999988079071,"initiatorType":"script","nextHopProtocol":"http/1.1","workerStart":0,"redirectStart":0,"redirectEnd":0,"fetchStart":28.900000005960464,"domainLookupStart":30.80000001192093,"domainLookupEnd":30.80000001192093,"connectStart":30.80000001192093,"connectEnd":31.099999994039536,"secureConnectionStart":0,"requestStart":31.400000005960464,"responseStart":39.30000001192093,"responseEnd":40.599999994039536,"transferSize":2306,"encodedBodySize":2006,"decodedBodySize":2006,"serverTiming":[]},{"name":"http://localhost:5173/@react-refresh","entryType":"resource","startTime":39.400000005960464,"duration":9.599999994039536,"initiatorType":"other","nextHopProtocol":"http/1.1","workerStart":0,"redirectStart":0,"redirectEnd":0,"fetchStart":39.400000005960464,"domainLookupStart":39.400000005960464,"domainLookupEnd":39.400000005960464,"connectStart":39.400000005960464,"connectEnd":39.400000005960464,"secureConnectionStart":0,"requestStart":41.69999998807907,"responseStart":43.69999998807907,"responseEnd":49,"transferSize":20955,"encodedBodySize":20655,"decodedBodySize":20655,"serverTiming":[]},{"name":"http://localhost:5173/node_modules/.vite/deps/react.js?v=39373c95","entryType":"resource","startTime":44.19999998807907,"duration":22.600000023841858,"initiatorType":"other","nextHopProtocol":"http/1.1","workerStart":0,"redirectStart":0,"redirectEnd":0,"fetchStart":44.19999998807907,"domainLookupStart":44.19999998807907,"domainLookupEnd":44.19999998807907,"connectStart":44.19999998807907,"connectEnd":44.19999998807907,"secureConnectionStart":0,"requestStart":50.30000001192093,"responseStart":64.80000001192093,"responseEnd":66.80000001192093,"transferSize":577,"encodedBodySize":277,"decodedBodySize":277,"serverTiming":[]},{"name":"http://localhost:5173/node_modules/.vite/deps/react-dom_client.js?v=39373c95","entryType":"resource","startTime":44.5,"duration":24.900000005960464,"initiatorType":"other","nextHopProtocol":"http/1.1","workerStart":0,"redirectStart":0,"redirectEnd":0,"fetchStart":44.5,"domainLookupStart":48.30000001192093,"domainLookupEnd":48.30000001192093,"connectStart":48.30000001192093,"connectEnd":48.599999994039536,"secureConnectionStart":0,"requestStart":50.5,"responseStart":68,"responseEnd":69.40000000596046,"transferSize":1625,"encodedBodySize":1325,"decodedBodySize":1325,"serverTiming":[]},{"name":"http://localhost:5173/src/App.jsx?t=1665146093538","entryType":"resource","startTime":44.599999994039536,"duration":33.30000001192093,"initiatorType":"other","nextHopProtocol":"http/1.1","workerStart":0,"redirectStart":0,"redirectEnd":0,"fetchStart":44.599999994039536,"domainLookupStart":48.69999998807907,"domainLookupEnd":48.69999998807907,"connectStart":48.69999998807907,"connectEnd":49,"secureConnectionStart":0,"requestStart":50.599999994039536,"responseStart":74.90000000596046,"responseEnd":77.90000000596046,"transferSize":16722,"encodedBodySize":16422,"decodedBodySize":16422,"serverTiming":[]},{"name":"http://localhost:5173/src/index.css?t=1665146093538","entryType":"resource","startTime":44.900000005960464,"duration":24.900000005960464,"initiatorType":"other","nextHopProtocol":"http/1.1","workerStart":0,"redirectStart":0,"redirectEnd":0,"fetchStart":44.900000005960464,"domainLookupStart":44.900000005960464,"domainLookupEnd":44.900000005960464,"connectStart":44.900000005960464,"connectEnd":44.900000005960464,"secureConnectionStart":0,"requestStart":50.400000005960464,"responseStart":67,"responseEnd":69.80000001192093,"transferSize":82695,"encodedBodySize":82395,"decodedBodySize":82395,"serverTiming":[]},{"name":"http://localhost:5173/@id/__x00__react/jsx-dev-runtime","entryType":"resource","startTime":45.099999994039536,"duration":32.400000005960464,"initiatorType":"other","nextHopProtocol":"http/1.1","workerStart":0,"redirectStart":0,"redirectEnd":0,"fetchStart":45.099999994039536,"domainLookupStart":49.599999994039536,"domainLookupEnd":49.599999994039536,"connectStart":49.599999994039536,"connectEnd":50,"secureConnectionStart":0,"requestStart":50.599999994039536,"responseStart":75.69999998807907,"responseEnd":77.5,"transferSize":556,"encodedBodySize":256,"decodedBodySize":256,"serverTiming":[]},{"name":"http://localhost:5173/node_modules/.pnpm/vite@3.1.5/node_modules/vite/dist/client/env.mjs","entryType":"resource","startTime":45.900000005960464,"duration":41.400000005960464,"initiatorType":"other","nextHopProtocol":"http/1.1","workerStart":0,"redirectStart":0,"redirectEnd":0,"fetchStart":45.900000005960464,"domainLookupStart":50.099999994039536,"domainLookupEnd":50.099999994039536,"connectStart":50.099999994039536,"connectEnd":50.30000001192093,"secureConnectionStart":0,"requestStart":50.69999998807907,"responseStart":85.5,"responseEnd":87.30000001192093,"transferSize":3514,"encodedBodySize":3214,"decodedBodySize":3214,"serverTiming":[]},{"name":"http://localhost:5173/node_modules/.vite/deps/chunk-CX7BBZXL.js?v=39373c95","entryType":"resource","startTime":72.80000001192093,"duration":31.19999998807907,"initiatorType":"other","nextHopProtocol":"http/1.1","workerStart":0,"redirectStart":0,"redirectEnd":0,"fetchStart":72.80000001192093,"domainLookupStart":72.80000001192093,"domainLookupEnd":72.80000001192093,"connectStart":72.80000001192093,"connectEnd":72.80000001192093,"secureConnectionStart":0,"requestStart":76.90000000596046,"responseStart":96.40000000596046,"responseEnd":104,"transferSize":73666,"encodedBodySize":73366,"decodedBodySize":73366,"serverTiming":[]},{"name":"http://localhost:5173/node_modules/.vite/deps/chunk-TWLJ45QX.js?v=39373c95","entryType":"resource","startTime":73.09999999403954,"duration":29.400000005960464,"initiatorType":"other","nextHopProtocol":"http/1.1","workerStart":0,"redirectStart":0,"redirectEnd":0,"fetchStart":73.09999999403954,"domainLookupStart":73.09999999403954,"domainLookupEnd":73.09999999403954,"connectStart":73.09999999403954,"connectEnd":73.09999999403954,"secureConnectionStart":0,"requestStart":77.40000000596046,"responseStart":98.30000001192093,"responseEnd":102.5,"transferSize":1414,"encodedBodySize":1114,"decodedBodySize":1114,"serverTiming":[]},{"name":"http://localhost:5173/node_modules/.vite/deps/chunk-DYF7DYP5.js?v=39373c95","entryType":"resource","startTime":73.30000001192093,"duration":33.599999994039536,"initiatorType":"other","nextHopProtocol":"http/1.1","workerStart":0,"redirectStart":0,"redirectEnd":0,"fetchStart":73.30000001192093,"domainLookupStart":73.30000001192093,"domainLookupEnd":73.30000001192093,"connectStart":73.30000001192093,"connectEnd":73.30000001192093,"secureConnectionStart":0,"requestStart":77.69999998807907,"responseStart":99.40000000596046,"responseEnd":106.90000000596046,"transferSize":906108,"encodedBodySize":905808,"decodedBodySize":905808,"serverTiming":[]},{"name":"http://localhost:5173/node_modules/.vite/deps/react-router-dom.js?v=39373c95","entryType":"resource","startTime":79.5,"duration":25,"initiatorType":"other","nextHopProtocol":"http/1.1","workerStart":0,"redirectStart":0,"redirectEnd":0,"fetchStart":79.5,"domainLookupStart":79.5,"domainLookupEnd":79.5,"connectStart":79.5,"connectEnd":79.5,"secureConnectionStart":0,"requestStart":81.59999999403954,"responseStart":100.19999998807907,"responseEnd":104.5,"transferSize":120753,"encodedBodySize":120453,"decodedBodySize":120453,"serverTiming":[]},{"name":"http://localhost:5173/src/Home.jsx","entryType":"resource","startTime":79.69999998807907,"duration":24,"initiatorType":"other","nextHopProtocol":"http/1.1","workerStart":0,"redirectStart":0,"redirectEnd":0,"fetchStart":79.69999998807907,"domainLookupStart":79.69999998807907,"domainLookupEnd":79.69999998807907,"connectStart":79.69999998807907,"connectEnd":79.69999998807907,"secureConnectionStart":0,"requestStart":81.80000001192093,"responseStart":101,"responseEnd":103.69999998807907,"transferSize":7634,"encodedBodySize":7334,"decodedBodySize":7334,"serverTiming":[]},{"name":"http://localhost:5173/node_modules/.vite/deps/react_jsx-dev-runtime.js?v=39373c95","entryType":"resource","startTime":80,"duration":22,"initiatorType":"other","nextHopProtocol":"http/1.1","workerStart":0,"redirectStart":0,"redirectEnd":0,"fetchStart":80,"domainLookupStart":80,"domainLookupEnd":80,"connectStart":80,"connectEnd":80,"secureConnectionStart":0,"requestStart":87.69999998807907,"responseStart":94.5,"responseEnd":102,"transferSize":35865,"encodedBodySize":35565,"decodedBodySize":35565,"serverTiming":[]},{"name":"http://localhost:5173/src/context-provider/index.jsx","entryType":"resource","startTime":224.80000001192093,"duration":2.399999976158142,"initiatorType":"other","nextHopProtocol":"http/1.1","workerStart":0,"redirectStart":0,"redirectEnd":0,"fetchStart":224.80000001192093,"domainLookupStart":224.80000001192093,"domainLookupEnd":224.80000001192093,"connectStart":224.80000001192093,"connectEnd":224.80000001192093,"secureConnectionStart":0,"requestStart":225.59999999403954,"responseStart":226.40000000596046,"responseEnd":227.19999998807907,"transferSize":4116,"encodedBodySize":3816,"decodedBodySize":3816,"serverTiming":[]},{"name":"first-paint","entryType":"paint","startTime":261.30000001192093,"duration":0},{"name":"first-contentful-paint","entryType":"paint","startTime":261.30000001192093,"duration":0},{"name":"http://localhost:5173/src/context-provider/Budget.jsx","entryType":"resource","startTime":261.80000001192093,"duration":4.0999999940395355,"initiatorType":"other","nextHopProtocol":"http/1.1","workerStart":0,"redirectStart":0,"redirectEnd":0,"fetchStart":261.80000001192093,"domainLookupStart":261.80000001192093,"domainLookupEnd":261.80000001192093,"connectStart":261.80000001192093,"connectEnd":261.80000001192093,"secureConnectionStart":0,"requestStart":262.90000000596046,"responseStart":263.80000001192093,"responseEnd":265.90000000596046,"transferSize":10030,"encodedBodySize":9730,"decodedBodySize":9730,"serverTiming":[]},{"name":"http://localhost:5173/src/context-provider/BudgetProvider.jsx","entryType":"resource","startTime":262.19999998807907,"duration":4.200000017881393,"initiatorType":"other","nextHopProtocol":"http/1.1","workerStart":0,"redirectStart":0,"redirectEnd":0,"fetchStart":262.19999998807907,"domainLookupStart":262.19999998807907,"domainLookupEnd":262.19999998807907,"connectStart":262.19999998807907,"connectEnd":262.19999998807907,"secureConnectionStart":0,"requestStart":263.09999999403954,"responseStart":265,"responseEnd":266.40000000596046,"transferSize":17348,"encodedBodySize":17048,"decodedBodySize":17048,"serverTiming":[]},{"name":"http://localhost:5173/src/common/BudgetDatePicker.jsx","entryType":"resource","startTime":267.59999999403954,"duration":5.0999999940395355,"initiatorType":"other","nextHopProtocol":"http/1.1","workerStart":0,"redirectStart":0,"redirectEnd":0,"fetchStart":267.59999999403954,"domainLookupStart":267.59999999403954,"domainLookupEnd":267.59999999403954,"connectStart":267.59999999403954,"connectEnd":267.59999999403954,"secureConnectionStart":0,"requestStart":268.40000000596046,"responseStart":271.59999999403954,"responseEnd":272.69999998807907,"transferSize":9416,"encodedBodySize":9116,"decodedBodySize":9116,"serverTiming":[]},{"name":"http://localhost:5173/src/common/ActivityFilter.jsx","entryType":"resource","startTime":267.90000000596046,"duration":10.599999994039536,"initiatorType":"other","nextHopProtocol":"http/1.1","workerStart":0,"redirectStart":0,"redirectEnd":0,"fetchStart":267.90000000596046,"domainLookupStart":267.90000000596046,"domainLookupEnd":267.90000000596046,"connectStart":267.90000000596046,"connectEnd":267.90000000596046,"secureConnectionStart":0,"requestStart":270.30000001192093,"responseStart":273.30000001192093,"responseEnd":278.5,"transferSize":6575,"encodedBodySize":6275,"decodedBodySize":6275,"serverTiming":[]},{"name":"http://localhost:5173/src/context-provider/MonthlyBudgets.jsx","entryType":"resource","startTime":268.09999999403954,"duration":11.300000011920929,"initiatorType":"other","nextHopProtocol":"http/1.1","workerStart":0,"redirectStart":0,"redirectEnd":0,"fetchStart":268.09999999403954,"domainLookupStart":268.09999999403954,"domainLookupEnd":268.09999999403954,"connectStart":268.09999999403954,"connectEnd":268.09999999403954,"secureConnectionStart":0,"requestStart":270.40000000596046,"responseStart":274.69999998807907,"responseEnd":279.40000000596046,"transferSize":9480,"encodedBodySize":9180,"decodedBodySize":9180,"serverTiming":[]},{"name":"http://localhost:5173/src/common/InPlaceEditor.jsx","entryType":"resource","startTime":268.40000000596046,"duration":11.199999988079071,"initiatorType":"other","nextHopProtocol":"http/1.1","workerStart":0,"redirectStart":0,"redirectEnd":0,"fetchStart":268.40000000596046,"domainLookupStart":268.40000000596046,"domainLookupEnd":268.40000000596046,"connectStart":268.40000000596046,"connectEnd":268.40000000596046,"secureConnectionStart":0,"requestStart":270.5,"responseStart":275.69999998807907,"responseEnd":279.59999999403954,"transferSize":6826,"encodedBodySize":6526,"decodedBodySize":6526,"serverTiming":[]},{"name":"http://localhost:5173/src/utils/budget-utils.js","entryType":"resource","startTime":268.59999999403954,"duration":11.200000017881393,"initiatorType":"other","nextHopProtocol":"http/1.1","workerStart":0,"redirectStart":0,"redirectEnd":0,"fetchStart":268.59999999403954,"domainLookupStart":268.59999999403954,"domainLookupEnd":268.59999999403954,"connectStart":268.59999999403954,"connectEnd":268.59999999403954,"secureConnectionStart":0,"requestStart":270.59999999403954,"responseStart":276.59999999403954,"responseEnd":279.80000001192093,"transferSize":5152,"encodedBodySize":4852,"decodedBodySize":4852,"serverTiming":[]},{"name":"http://localhost:5173/src/utils/index.js","entryType":"resource","startTime":268.80000001192093,"duration":10.299999982118607,"initiatorType":"other","nextHopProtocol":"http/1.1","workerStart":0,"redirectStart":0,"redirectEnd":0,"fetchStart":268.80000001192093,"domainLookupStart":268.80000001192093,"domainLookupEnd":268.80000001192093,"connectStart":268.80000001192093,"connectEnd":268.80000001192093,"secureConnectionStart":0,"requestStart":271,"responseStart":277.59999999403954,"responseEnd":279.09999999403954,"transferSize":963,"encodedBodySize":663,"decodedBodySize":663,"serverTiming":[]},{"name":"http://localhost:5173/src/utils/budget-model-generator.js","entryType":"resource","startTime":273.40000000596046,"duration":14.599999994039536,"initiatorType":"other","nextHopProtocol":"http/1.1","workerStart":0,"redirectStart":0,"redirectEnd":0,"fetchStart":273.40000000596046,"domainLookupStart":273.40000000596046,"domainLookupEnd":273.40000000596046,"connectStart":273.40000000596046,"connectEnd":273.40000000596046,"secureConnectionStart":0,"requestStart":279.19999998807907,"responseStart":286.40000000596046,"responseEnd":288,"transferSize":1407,"encodedBodySize":1107,"decodedBodySize":1107,"serverTiming":[]},{"name":"http://localhost:5173/node_modules/.vite/deps/@mdi_js.js?v=39373c95","entryType":"resource","startTime":280.30000001192093,"duration":60.099999994039536,"initiatorType":"other","nextHopProtocol":"http/1.1","workerStart":0,"redirectStart":0,"redirectEnd":0,"fetchStart":280.30000001192093,"domainLookupStart":280.30000001192093,"domainLookupEnd":280.30000001192093,"connectStart":280.30000001192093,"connectEnd":280.30000001192093,"secureConnectionStart":0,"requestStart":281.19999998807907,"responseStart":291.90000000596046,"responseEnd":340.40000000596046,"transferSize":2755615,"encodedBodySize":2755315,"decodedBodySize":2755315,"serverTiming":[]},{"name":"http://localhost:5173/node_modules/.vite/deps/date-fns.js?v=39373c95","entryType":"resource","startTime":280.59999999403954,"duration":66,"initiatorType":"other","nextHopProtocol":"http/1.1","workerStart":0,"redirectStart":0,"redirectEnd":0,"fetchStart":280.59999999403954,"domainLookupStart":280.59999999403954,"domainLookupEnd":280.59999999403954,"connectStart":280.59999999403954,"connectEnd":280.59999999403954,"secureConnectionStart":0,"requestStart":281.40000000596046,"responseStart":295.90000000596046,"responseEnd":346.59999999403954,"transferSize":371959,"encodedBodySize":371659,"decodedBodySize":371659,"serverTiming":[]},{"name":"http://localhost:5173/src/context-provider/MonthlyBudget.jsx","entryType":"resource","startTime":282.69999998807907,"duration":23.5,"initiatorType":"other","nextHopProtocol":"http/1.1","workerStart":0,"redirectStart":0,"redirectEnd":0,"fetchStart":282.69999998807907,"domainLookupStart":282.69999998807907,"domainLookupEnd":282.69999998807907,"connectStart":282.69999998807907,"connectEnd":282.69999998807907,"secureConnectionStart":0,"requestStart":283.69999998807907,"responseStart":298.80000001192093,"responseEnd":306.19999998807907,"transferSize":3380,"encodedBodySize":3080,"decodedBodySize":3080,"serverTiming":[]},{"name":"http://localhost:5173/src/utils/empty.js","entryType":"resource","startTime":283.09999999403954,"duration":25.200000017881393,"initiatorType":"other","nextHopProtocol":"http/1.1","workerStart":0,"redirectStart":0,"redirectEnd":0,"fetchStart":283.09999999403954,"domainLookupStart":283.09999999403954,"domainLookupEnd":283.09999999403954,"connectStart":283.09999999403954,"connectEnd":283.09999999403954,"secureConnectionStart":0,"requestStart":288.30000001192093,"responseStart":301.90000000596046,"responseEnd":308.30000001192093,"transferSize":930,"encodedBodySize":630,"decodedBodySize":630,"serverTiming":[]},{"name":"http://localhost:5173/src/utils/uuid.js","entryType":"resource","startTime":283.30000001192093,"duration":25.299999982118607,"initiatorType":"other","nextHopProtocol":"http/1.1","workerStart":0,"redirectStart":0,"redirectEnd":0,"fetchStart":283.30000001192093,"domainLookupStart":283.30000001192093,"domainLookupEnd":283.30000001192093,"connectStart":283.30000001192093,"connectEnd":283.30000001192093,"secureConnectionStart":0,"requestStart":288.5,"responseStart":303.40000000596046,"responseEnd":308.59999999403954,"transferSize":665,"encodedBodySize":365,"decodedBodySize":365,"serverTiming":[]},{"name":"http://localhost:5173/src/utils/copy.js","entryType":"resource","startTime":283.5,"duration":23.69999998807907,"initiatorType":"other","nextHopProtocol":"http/1.1","workerStart":0,"redirectStart":0,"redirectEnd":0,"fetchStart":283.5,"domainLookupStart":283.5,"domainLookupEnd":283.5,"connectStart":283.5,"connectEnd":283.5,"secureConnectionStart":0,"requestStart":288.59999999403954,"responseStart":300.5,"responseEnd":307.19999998807907,"transferSize":415,"encodedBodySize":115,"decodedBodySize":115,"serverTiming":[]},{"name":"http://localhost:5173/src/utils/noop.js","entryType":"resource","startTime":283.90000000596046,"duration":39.400000005960464,"initiatorType":"other","nextHopProtocol":"http/1.1","workerStart":0,"redirectStart":0,"redirectEnd":0,"fetchStart":283.90000000596046,"domainLookupStart":283.90000000596046,"domainLookupEnd":283.90000000596046,"connectStart":283.90000000596046,"connectEnd":283.90000000596046,"secureConnectionStart":0,"requestStart":310.59999999403954,"responseStart":314.59999999403954,"responseEnd":323.30000001192093,"transferSize":343,"encodedBodySize":43,"decodedBodySize":43,"serverTiming":[]},{"name":"http://localhost:5173/src/utils/numbers.js","entryType":"resource","startTime":284,"duration":39.80000001192093,"initiatorType":"other","nextHopProtocol":"http/1.1","workerStart":0,"redirectStart":0,"redirectEnd":0,"fetchStart":284,"domainLookupStart":284,"domainLookupEnd":284,"connectStart":284,"connectEnd":284,"secureConnectionStart":0,"requestStart":310.69999998807907,"responseStart":316,"responseEnd":323.80000001192093,"transferSize":481,"encodedBodySize":181,"decodedBodySize":181,"serverTiming":[]},{"name":"http://localhost:5173/src/utils/isObject.js","entryType":"resource","startTime":284.30000001192093,"duration":39.89999997615814,"initiatorType":"other","nextHopProtocol":"http/1.1","workerStart":0,"redirectStart":0,"redirectEnd":0,"fetchStart":284.30000001192093,"domainLookupStart":284.30000001192093,"domainLookupEnd":284.30000001192093,"connectStart":284.30000001192093,"connectEnd":284.30000001192093,"secureConnectionStart":0,"requestStart":310.69999998807907,"responseStart":317.59999999403954,"responseEnd":324.19999998807907,"transferSize":380,"encodedBodySize":80,"decodedBodySize":80,"serverTiming":[]},{"name":"http://localhost:5173/src/utils/reducer.js","entryType":"resource","startTime":284.5,"duration":40,"initiatorType":"other","nextHopProtocol":"http/1.1","workerStart":0,"redirectStart":0,"redirectEnd":0,"fetchStart":284.5,"domainLookupStart":284.5,"domainLookupEnd":284.5,"connectStart":284.5,"connectEnd":284.5,"secureConnectionStart":0,"requestStart":310.80000001192093,"responseStart":319.19999998807907,"responseEnd":324.5,"transferSize":688,"encodedBodySize":388,"decodedBodySize":388,"serverTiming":[]},{"name":"http://localhost:5173/src/utils/serialize.js","entryType":"resource","startTime":284.59999999403954,"duration":47.30000001192093,"initiatorType":"other","nextHopProtocol":"http/1.1","workerStart":0,"redirectStart":0,"redirectEnd":0,"fetchStart":284.59999999403954,"domainLookupStart":284.59999999403954,"domainLookupEnd":284.59999999403954,"connectStart":284.59999999403954,"connectEnd":284.59999999403954,"secureConnectionStart":0,"requestStart":325.09999999403954,"responseStart":326,"responseEnd":331.90000000596046,"transferSize":373,"encodedBodySize":73,"decodedBodySize":73,"serverTiming":[]},{"name":"http://localhost:5173/src/utils/deserialize.js","entryType":"resource","startTime":284.69999998807907,"duration":47.80000001192093,"initiatorType":"other","nextHopProtocol":"http/1.1","workerStart":0,"redirectStart":0,"redirectEnd":0,"fetchStart":284.69999998807907,"domainLookupStart":284.69999998807907,"domainLookupEnd":284.69999998807907,"connectStart":284.69999998807907,"connectEnd":284.69999998807907,"secureConnectionStart":0,"requestStart":325.19999998807907,"responseStart":327.40000000596046,"responseEnd":332.5,"transferSize":537,"encodedBodySize":237,"decodedBodySize":237,"serverTiming":[]},{"name":"http://localhost:5173/src/utils/dateReviver.js","entryType":"resource","startTime":285,"duration":48.30000001192093,"initiatorType":"other","nextHopProtocol":"http/1.1","workerStart":0,"redirectStart":0,"redirectEnd":0,"fetchStart":285,"domainLookupStart":285,"domainLookupEnd":285,"connectStart":285,"connectEnd":285,"secureConnectionStart":0,"requestStart":325.40000000596046,"responseStart":328.90000000596046,"responseEnd":333.30000001192093,"transferSize":611,"encodedBodySize":311,"decodedBodySize":311,"serverTiming":[]},{"name":"http://localhost:5173/src/utils/category-generator.js","entryType":"resource","startTime":289.09999999403954,"duration":45.599999994039536,"initiatorType":"other","nextHopProtocol":"http/1.1","workerStart":0,"redirectStart":0,"redirectEnd":0,"fetchStart":289.09999999403954,"domainLookupStart":289.09999999403954,"domainLookupEnd":289.09999999403954,"connectStart":289.09999999403954,"connectEnd":289.09999999403954,"secureConnectionStart":0,"requestStart":325.5,"responseStart":330.40000000596046,"responseEnd":334.69999998807907,"transferSize":8430,"encodedBodySize":8130,"decodedBodySize":8130,"serverTiming":[]},{"name":"http://localhost:5173/src/context-provider/Categories.jsx","entryType":"resource","startTime":307.30000001192093,"duration":46.39999997615814,"initiatorType":"other","nextHopProtocol":"http/1.1","workerStart":0,"redirectStart":0,"redirectEnd":0,"fetchStart":307.30000001192093,"domainLookupStart":307.30000001192093,"domainLookupEnd":307.30000001192093,"connectStart":307.30000001192093,"connectEnd":307.30000001192093,"secureConnectionStart":0,"requestStart":335.19999998807907,"responseStart":352.30000001192093,"responseEnd":353.69999998807907,"transferSize":10590,"encodedBodySize":10290,"decodedBodySize":10290,"serverTiming":[]},{"name":"http://localhost:5173/src/utils/isJson.js","entryType":"resource","startTime":334.90000000596046,"duration":21.400000005960464,"initiatorType":"other","nextHopProtocol":"http/1.1","workerStart":0,"redirectStart":0,"redirectEnd":0,"fetchStart":334.90000000596046,"domainLookupStart":334.90000000596046,"domainLookupEnd":334.90000000596046,"connectStart":334.90000000596046,"connectEnd":334.90000000596046,"secureConnectionStart":0,"requestStart":339,"responseStart":353.90000000596046,"responseEnd":356.30000001192093,"transferSize":422,"encodedBodySize":122,"decodedBodySize":122,"serverTiming":[]},{"name":"http://localhost:5173/node_modules/.vite/deps/date-fns_add.js?v=39373c95","entryType":"resource","startTime":337,"duration":19.69999998807907,"initiatorType":"other","nextHopProtocol":"http/1.1","workerStart":0,"redirectStart":0,"redirectEnd":0,"fetchStart":337,"domainLookupStart":337,"domainLookupEnd":337,"connectStart":337,"connectEnd":337,"secureConnectionStart":0,"requestStart":339.30000001192093,"responseStart":355,"responseEnd":356.69999998807907,"transferSize":583,"encodedBodySize":283,"decodedBodySize":283,"serverTiming":[]},{"name":"http://localhost:5173/node_modules/.vite/deps/chunk-WCERTD75.js?v=39373c95","entryType":"resource","startTime":357.09999999403954,"duration":2.7000000178813934,"initiatorType":"other","nextHopProtocol":"http/1.1","workerStart":0,"redirectStart":0,"redirectEnd":0,"fetchStart":357.09999999403954,"domainLookupStart":357.09999999403954,"domainLookupEnd":357.09999999403954,"connectStart":357.09999999403954,"connectEnd":357.09999999403954,"secureConnectionStart":0,"requestStart":357.69999998807907,"responseStart":358.59999999403954,"responseEnd":359.80000001192093,"transferSize":5007,"encodedBodySize":4707,"decodedBodySize":4707,"serverTiming":[]},{"name":"http://localhost:5173/src/context-provider/Category.jsx","entryType":"resource","startTime":362,"duration":11.800000011920929,"initiatorType":"other","nextHopProtocol":"http/1.1","workerStart":0,"redirectStart":0,"redirectEnd":0,"fetchStart":362,"domainLookupStart":362,"domainLookupEnd":362,"connectStart":362,"connectEnd":362,"secureConnectionStart":0,"requestStart":363.40000000596046,"responseStart":371,"responseEnd":373.80000001192093,"transferSize":9506,"encodedBodySize":9206,"decodedBodySize":9206,"serverTiming":[]},{"name":"http://localhost:5173/src/common/Accordion.jsx","entryType":"resource","startTime":362.19999998807907,"duration":12.100000023841858,"initiatorType":"other","nextHopProtocol":"http/1.1","workerStart":0,"redirectStart":0,"redirectEnd":0,"fetchStart":362.19999998807907,"domainLookupStart":362.19999998807907,"domainLookupEnd":362.19999998807907,"connectStart":362.19999998807907,"connectEnd":362.19999998807907,"secureConnectionStart":0,"requestStart":363.59999999403954,"responseStart":372.30000001192093,"responseEnd":374.30000001192093,"transferSize":7827,"encodedBodySize":7527,"decodedBodySize":7527,"serverTiming":[]},{"name":"http://localhost:5173/src/context-provider/Item.jsx","entryType":"resource","startTime":377.09999999403954,"duration":2.9000000059604645,"initiatorType":"other","nextHopProtocol":"http/1.1","workerStart":0,"redirectStart":0,"redirectEnd":0,"fetchStart":377.09999999403954,"domainLookupStart":377.09999999403954,"domainLookupEnd":377.09999999403954,"connectStart":377.09999999403954,"connectEnd":377.09999999403954,"secureConnectionStart":0,"requestStart":378.40000000596046,"responseStart":378.90000000596046,"responseEnd":380,"transferSize":12273,"encodedBodySize":11973,"decodedBodySize":11973,"serverTiming":[]},{"name":"http://localhost:5173/src/context-provider/Transaction.jsx","entryType":"resource","startTime":381.30000001192093,"duration":5.399999976158142,"initiatorType":"other","nextHopProtocol":"http/1.1","workerStart":0,"redirectStart":0,"redirectEnd":0,"fetchStart":381.30000001192093,"domainLookupStart":381.30000001192093,"domainLookupEnd":381.30000001192093,"connectStart":381.30000001192093,"connectEnd":381.30000001192093,"secureConnectionStart":0,"requestStart":382.80000001192093,"responseStart":384.5,"responseEnd":386.69999998807907,"transferSize":10866,"encodedBodySize":10566,"decodedBodySize":10566,"serverTiming":[]},{"name":"pointerdown","entryType":"first-input","startTime":578.5999999940395,"duration":8,"processingStart":580.5999999940395,"processingEnd":581.4000000059605,"cancelable":true}],"largestContentfulPaint":531.699,"totalBlockingTime":11}