{"perfEntries":[{"name":"http://localhost:4173/","entryType":"navigation","startTime":0,"duration":48.100000001490116,"initiatorType":"navigation","nextHopProtocol":"http/1.1","renderBlockingStatus":"blocking","workerStart":0,"redirectStart":0,"redirectEnd":0,"fetchStart":0.7000000029802322,"domainLookupStart":4.399999998509884,"domainLookupEnd":4.399999998509884,"connectStart":4.399999998509884,"connectEnd":4.899999998509884,"secureConnectionStart":0,"requestStart":5.100000001490116,"responseStart":8.5,"responseEnd":9.700000002980232,"transferSize":949,"encodedBodySize":649,"decodedBodySize":649,"serverTiming":[],"unloadEventStart":0,"unloadEventEnd":0,"domInteractive":24.899999998509884,"domContentLoadedEventStart":48.100000001490116,"domContentLoadedEventEnd":48.100000001490116,"domComplete":48.100000001490116,"loadEventStart":48.100000001490116,"loadEventEnd":48.100000001490116,"type":"navigate","redirectCount":0},{"name":"http://localhost:4173/assets/index.d2cb8674.js","entryType":"resource","startTime":15.200000002980232,"duration":15.899999998509884,"initiatorType":"script","nextHopProtocol":"http/1.1","renderBlockingStatus":"non-blocking","workerStart":0,"redirectStart":0,"redirectEnd":0,"fetchStart":15.200000002980232,"domainLookupStart":15.200000002980232,"domainLookupEnd":15.200000002980232,"connectStart":15.200000002980232,"connectEnd":15.200000002980232,"secureConnectionStart":0,"requestStart":15.799999997019768,"responseStart":24.100000001490116,"responseEnd":31.100000001490116,"transferSize":53735,"encodedBodySize":53435,"decodedBodySize":164521,"serverTiming":[]},{"name":"http://localhost:4173/assets/index.ee45aa9c.css","entryType":"resource","startTime":15.5,"duration":12.5,"initiatorType":"link","nextHopProtocol":"http/1.1","renderBlockingStatus":"blocking","workerStart":0,"redirectStart":0,"redirectEnd":0,"fetchStart":15.5,"domainLookupStart":15.700000002980232,"domainLookupEnd":15.700000002980232,"connectStart":15.700000002980232,"connectEnd":16.399999998509884,"secureConnectionStart":0,"requestStart":16.5,"responseStart":25.200000002980232,"responseEnd":28,"transferSize":12153,"encodedBodySize":11853,"decodedBodySize":67660,"serverTiming":[]},{"name":"first-paint","entryType":"paint","startTime":88.39999999850988,"duration":0},{"name":"first-contentful-paint","entryType":"paint","startTime":88.39999999850988,"duration":0},{"name":"pointerdown","entryType":"first-input","startTime":129.70000000298023,"duration":40,"processingStart":132.5,"processingEnd":133,"cancelable":true},{"name":"http://localhost:4173/assets/index.f74d1225.js","entryType":"resource","startTime":137.29999999701977,"duration":10.900000005960464,"initiatorType":"other","nextHopProtocol":"http/1.1","renderBlockingStatus":"non-blocking","workerStart":0,"redirectStart":0,"redirectEnd":0,"fetchStart":137.29999999701977,"domainLookupStart":137.29999999701977,"domainLookupEnd":137.29999999701977,"connectStart":137.29999999701977,"connectEnd":137.29999999701977,"secureConnectionStart":0,"requestStart":137.89999999850988,"responseStart":146.70000000298023,"responseEnd":148.20000000298023,"transferSize":2405,"encodedBodySize":2105,"decodedBodySize":6535,"serverTiming":[]},{"name":"http://localhost:4173/assets/InPlaceEditor.5050b814.js","entryType":"resource","startTime":137.79999999701977,"duration":179.60000000149012,"initiatorType":"other","nextHopProtocol":"http/1.1","renderBlockingStatus":"non-blocking","workerStart":0,"redirectStart":0,"redirectEnd":0,"fetchStart":137.79999999701977,"domainLookupStart":137.79999999701977,"domainLookupEnd":137.79999999701977,"connectStart":137.79999999701977,"connectEnd":137.79999999701977,"secureConnectionStart":0,"requestStart":138,"responseStart":146.89999999850988,"responseEnd":317.3999999985099,"transferSize":988844,"encodedBodySize":988544,"decodedBodySize":3748131,"serverTiming":[]}],"largestContentfulPaint":88.399,"totalBlockingTime":0}